src/fpga/spi_shifter.v
module spi_byte_shifter #(
    parameter integer CLK_DIV = 4  // sysclk ticks per half SCK
) (
    input  wire clk,
    input  wire reset_n,
    input  wire start,
    input  wire [7:0] tx_byte,
    input  wire mosi_oe,           // drive MOSI when 1
    output reg  [7:0] rx_byte,
    output reg  busy,
    output reg  sck,
    output reg  mosi,
    input  wire miso,
    output reg  done
);
    reg [7:0] shreg;
    reg [3:0] bitcnt;
    reg [$clog2(CLK_DIV*2)-1:0] divcnt;

    always @(posedge clk or negedge reset_n) begin
        if (!reset_n) begin
            busy <= 0; done <= 0; sck <= 0; mosi <= 0; rx_byte <= 0;
            bitcnt <= 0; divcnt <= 0; shreg <= 0;
        end else begin
            done <= 1'b0;
            if (start && !busy) begin
                busy   <= 1'b1;
                shreg  <= tx_byte;
                bitcnt <= 4'd8;
                divcnt <= 0;
                sck    <= 1'b0;
                mosi   <= tx_byte[7];
            end else if (busy) begin
                divcnt <= divcnt + 1'b1;
                if (divcnt == CLK_DIV-1) begin
                    sck <= 1'b1; // rising edge: sample MISO
                end else if (divcnt == CLK_DIV*2-1) begin
                    // falling edge: shift out next bit
                    divcnt <= 0;
                    shreg <= {shreg[6:0], miso};
                    bitcnt <= bitcnt - 1'b1;
                    sck <= 1'b0;
                    mosi <= shreg[6];
                    if (bitcnt == 1) begin
                        busy <= 1'b0;
                        done <= 1'b1;
                        rx_byte <= {shreg[6:0], miso};
                        mosi <= 1'b0;
                    end
                end
            end
            if (!mosi_oe) mosi <= 1'b0; // tri-state externally with OBUFT if needed
        end
    end
endmodule

test/sim/spi_byte_shifter_tb.v
// This is to verify the MSB-first shift, the spi timing and the "done" timing.

`timescale 1ns/1ps

module spi_byte_shifter_tb;

    reg clk = 0;
    reg reset_n = 0;
    reg start = 0;
    reg [7:0] tx_byte = 8'hA5;
    wire [7:0] rx_byte;
    wire busy, done;
    wire sck, mosi;
    reg miso = 1;

    always #5 clk = ~clk; // 100 MHz

    spi_byte_shifter dut (
        .clk(clk),
        .reset_n(reset_n),
        .start(start),
        .tx_byte(tx_byte),
        .mosi_oe(1'b1),
        .rx_byte(rx_byte),
        .busy(busy),
        .sck(sck),
        .mosi(mosi),
        .miso(miso),
        .done(done)
    );

    initial begin
        $dumpfile("spi_byte_shifter_tb.vcd");
        $dumpvars(0, spi_byte_shifter_tb);

        reset_n = 0;
        #50 reset_n = 1;

        #50 start = 1;
        #10 start = 0;

        wait(done);
        $display("RX byte = %h", rx_byte);

        #200;
        $finish;
    end
endmodule

test/spi_byte_shifter_tb.vcd
$date
	Sat Mar 07 13:50:34 2026
$end
$version
	Icarus Verilog
$end
$timescale
	1ps
$end
$scope module spi_byte_shifter_tb $end
$var wire 1 ! sck $end
$var wire 8 " rx_byte [7:0] $end
$var wire 1 # mosi $end
$var wire 1 $ done $end
$var wire 1 % busy $end
$var reg 1 & clk $end
$var reg 1 ' miso $end
$var reg 1 ( reset_n $end
$var reg 1 ) start $end
$var reg 8 * tx_byte [7:0] $end
$scope module dut $end
$var wire 1 & clk $end
$var wire 1 ' miso $end
$var wire 1 + mosi_oe $end
$var wire 1 ( reset_n $end
$var wire 1 ) start $end
$var wire 8 , tx_byte [7:0] $end
$var parameter 32 - CLK_DIV $end
$var reg 4 . bitcnt [3:0] $end
$var reg 1 % busy $end
$var reg 3 / divcnt [2:0] $end
$var reg 1 $ done $end
$var reg 1 # mosi $end
$var reg 8 0 rx_byte [7:0] $end
$var reg 1 ! sck $end
$var reg 8 1 shreg [7:0] $end
$upscope $end
$upscope $end
$enddefinitions $end
$comment Show the parameter values. $end
$dumpall
b100 -
$end
#0
$dumpvars
bx 1
bx 0
bx /
bx .
b10100101 ,
1+
b10100101 *
0)
0(
1'
0&
x%
x$
x#
bx "
x!
$end
#5000
b0 1
b0 /
b0 .
b0 "
b0 0
0#
0!
0$
0%
1&
#10000
0&
#15000
1&
#20000
0&
#25000
1&
#30000
0&
#35000
1&
#40000
0&
#45000
1&
#50000
0&
1(
#55000
1&
#60000
0&
#65000
1&
#70000
0&
#75000
1&
#80000
0&
#85000
1&
#90000
0&
#95000
1&
#100000
0&
1)
#105000
1#
b1000 .
b10100101 1
1%
1&
#110000
0&
0)
#115000
b1 /
1&
#120000
0&
#125000
b10 /
1&
#130000
0&
#135000
b11 /
1&
#140000
0&
#145000
1!
b100 /
1&
#150000
0&
#155000
b101 /
1&
#160000
0&
#165000
b110 /
1&
#170000
0&
#175000
b111 /
1&
#180000
0&
#185000
0#
0!
b111 .
b1001011 1
b0 /
1&
#190000
0&
#195000
b1 /
1&
#200000
0&
#205000
b10 /
1&
#210000
0&
#215000
b11 /
1&
#220000
0&
#225000
1!
b100 /
1&
#230000
0&
#235000
b101 /
1&
#240000
0&
#245000
b110 /
1&
#250000
0&
#255000
b111 /
1&
#260000
0&
#265000
1#
0!
b110 .
b10010111 1
b0 /
1&
#270000
0&
#275000
b1 /
1&
#280000
0&
#285000
b10 /
1&
#290000
0&
#295000
b11 /
1&
#300000
0&
#305000
1!
b100 /
1&
#310000
0&
#315000
b101 /
1&
#320000
0&
#325000
b110 /
1&
#330000
0&
#335000
b111 /
1&
#340000
0&
#345000
0#
0!
b101 .
b101111 1
b0 /
1&
#350000
0&
#355000
b1 /
1&
#360000
0&
#365000
b10 /
1&
#370000
0&
#375000
b11 /
1&
#380000
0&
#385000
1!
b100 /
1&
#390000
0&
#395000
b101 /
1&
#400000
0&
#405000
b110 /
1&
#410000
0&
#415000
b111 /
1&
#420000
0&
#425000
0!
b100 .
b1011111 1
b0 /
1&
#430000
0&
#435000
b1 /
1&
#440000
0&
#445000
b10 /
1&
#450000
0&
#455000
b11 /
1&
#460000
0&
#465000
1!
b100 /
1&
#470000
0&
#475000
b101 /
1&
#480000
0&
#485000
b110 /
1&
#490000
0&
#495000
b111 /
1&
#500000
0&
#505000
1#
0!
b11 .
b10111111 1
b0 /
1&
#510000
0&
#515000
b1 /
1&
#520000
0&
#525000
b10 /
1&
#530000
0&
#535000
b11 /
1&
#540000
0&
#545000
1!
b100 /
1&
#550000
0&
#555000
b101 /
1&
#560000
0&
#565000
b110 /
1&
#570000
0&
#575000
b111 /
1&
#580000
0&
#585000
0#
0!
b10 .
b1111111 1
b0 /
1&
#590000
0&
#595000
b1 /
1&
#600000
0&
#605000
b10 /
1&
#610000
0&
#615000
b11 /
1&
#620000
0&
#625000
1!
b100 /
1&
#630000
0&
#635000
b101 /
1&
#640000
0&
#645000
b110 /
1&
#650000
0&
#655000
b111 /
1&
#660000
0&
#665000
1#
0!
b1 .
b11111111 1
b0 /
1&
#670000
0&
#675000
b1 /
1&
#680000
0&
#685000
b10 /
1&
#690000
0&
#695000
b11 /
1&
#700000
0&
#705000
1!
b100 /
1&
#710000
0&
#715000
b101 /
1&
#720000
0&
#725000
b110 /
1&
#730000
0&
#735000
b111 /
1&
#740000
0&
#745000
0#
b11111111 "
b11111111 0
1$
0%
0!
b0 .
b0 /
1&
#750000
0&
#755000
0$
1&
