src/fpga/spi_slave_rx.v
// spi_slave_rx.v
// SPI slave receiver for 16-bit words (Mode 0: CPOL=0, CPHA=0), MSB-first.
// CDC from spi_sclk domain -> clk_system domain uses a request toggle only.
// The sample source is much slower than clk_system, so a single-word holding
// register is sufficient and avoids requiring extra SPI edges between frames.

module spi_slave_rx (
    input  wire        clk_system,
    input  wire        rst_n,

    // SPI (from MCU)
    input  wire        spi_sclk,
    input  wire        spi_cs_n,
    input  wire        spi_mosi,

    // Output (clk_system domain)
    output reg  [15:0] ecg_data_out,
    output reg         data_valid
);

    // Local reset synchronizer for the always-running system clock domain.
    reg [1:0] rst_sys_sync;

    wire rst_n_sys = rst_sys_sync[1];

    // -----------------------------
    // SPI clock domain registers
    // -----------------------------
    reg [15:0] rx_shift;
    reg [3:0]  bit_cnt;

    reg [15:0] data_latch_spi;   // stable until the next word completes
    reg        req_toggle_spi;   // toggles when a word is ready

    // Reset deassertion synchronized into system domain.
    always @(posedge clk_system or negedge rst_n) begin
        if (!rst_n) begin
            rst_sys_sync <= 2'b00;
        end else begin
            rst_sys_sync <= {rst_sys_sync[0], 1'b1};
        end
    end

    // Main SPI capture (Mode 0: sample MOSI on rising edge).
    always @(posedge spi_sclk or negedge rst_n) begin
        if (!rst_n) begin
            rx_shift       <= 16'd0;
            bit_cnt        <= 4'd0;
            data_latch_spi <= 16'd0;
            req_toggle_spi <= 1'b0;
        end else begin
            if (spi_cs_n) begin
                bit_cnt <= 4'd0;
            end else begin
                // shift in bits MSB-first
                rx_shift <= {rx_shift[14:0], spi_mosi};

                if (bit_cnt == 4'd15) begin
                    data_latch_spi <= {rx_shift[14:0], spi_mosi};
                    req_toggle_spi <= ~req_toggle_spi;
                    bit_cnt        <= 4'd0;
                end else begin
                    bit_cnt <= bit_cnt + 4'd1;
                end
            end
        end
    end

    // -----------------------------
    // System clock domain (CDC)
    // -----------------------------
    reg req_sync1_sys, req_sync2_sys;
    reg req_prev_sys;

    // Synchronize req toggle into system domain.
    always @(posedge clk_system) begin
        if (!rst_n_sys) begin
            req_sync1_sys <= 1'b0;
            req_sync2_sys <= 1'b0;
        end else begin
            req_sync1_sys <= req_toggle_spi;
            req_sync2_sys <= req_sync1_sys;
        end
    end

    // Capture data on req toggle change, then toggle ack.
    always @(posedge clk_system) begin
        if (!rst_n_sys) begin
            ecg_data_out       <= 16'd0;
            data_valid         <= 1'b0;
            req_prev_sys       <= 1'b0;
        end else begin
            data_valid <= 1'b0;

            if (req_sync2_sys != req_prev_sys) begin
                req_prev_sys <= req_sync2_sys;

                // Safe because SPI side holds data_latch_spi stable until the next
                // complete 16-bit word arrives, which is much slower than clk_system.
                ecg_data_out <= data_latch_spi;
                data_valid   <= 1'b1;
            end
        end
    end

endmodule

test/sim/spi_slave_rx_tb.v
// This testbench is the most important one, as it checks 
// the MSB-first reception, CDC handshake, data_valid pulse, and no deadlock. 
`timescale 1ns/1ps

module spi_slave_rx_tb;

    reg clk_sys = 0;
    reg spi_sclk = 0;
    reg spi_cs_n = 1;
    reg spi_mosi = 0;
    reg rst_n = 1;

    wire [15:0] ecg_data_out;
    wire data_valid;

    // 27 MHz system clock (~37ns)
    always #18.5 clk_sys = ~clk_sys;

    spi_slave_rx dut (
        .clk_system(clk_sys),
        .rst_n(rst_n),
        .spi_sclk(spi_sclk),
        .spi_cs_n(spi_cs_n),
        .spi_mosi(spi_mosi),
        .ecg_data_out(ecg_data_out),
        .data_valid(data_valid)
    );

    task spi_send_word(input [15:0] word);
        integer i;
        begin
            spi_cs_n = 0;
            #50;
            for (i = 15; i >= 0; i = i - 1) begin
                spi_mosi = word[i];
                #50 spi_sclk = 1;
                #50 spi_sclk = 0;
            end
            #20;
            spi_cs_n = 1;
        end
    endtask

    initial begin
        $dumpfile("spi_slave_rx_tb.vcd");
        $dumpvars(0, spi_slave_rx_tb);

        $display("Starting spi_slave_rx TB");
        rst_n = 1'b1;
        #1;
        rst_n = 1'b0;
        #200;
        rst_n = 1'b1;
        #100;

        spi_send_word(16'h1234);
        spi_send_word(16'hABCD);
        spi_send_word(16'h0F0F);

        #2000;
        $finish;
    end

    always @(posedge data_valid) begin
        $display("RX @ %0t : %h", $time, ecg_data_out);
    end

endmodule

/*
Expected waveform behavior
data_valid pulses once per word
ecg_data_out matches exactly
No missed samples
*/

test/spi_slave_rx_tb.vcd
$date
	Sat Mar 07 13:48:09 2026
$end
$version
	Icarus Verilog
$end
$timescale
	1ps
$end
$scope module spi_slave_rx_tb $end
$var wire 16 ! ecg_data_out [15:0] $end
$var wire 1 " data_valid $end
$var reg 1 # clk_sys $end
$var reg 1 $ rst_n $end
$var reg 1 % spi_cs_n $end
$var reg 1 & spi_mosi $end
$var reg 1 ' spi_sclk $end
$scope module dut $end
$var wire 1 # clk_system $end
$var wire 1 $ rst_n $end
$var wire 1 % spi_cs_n $end
$var wire 1 & spi_mosi $end
$var wire 1 ' spi_sclk $end
$var wire 1 ( rst_n_sys $end
$var reg 4 ) bit_cnt [3:0] $end
$var reg 16 * data_latch_spi [15:0] $end
$var reg 1 " data_valid $end
$var reg 16 + ecg_data_out [15:0] $end
$var reg 1 , req_prev_sys $end
$var reg 1 - req_sync1_sys $end
$var reg 1 . req_sync2_sys $end
$var reg 1 / req_toggle_spi $end
$var reg 2 0 rst_sys_sync [1:0] $end
$var reg 16 1 rx_shift [15:0] $end
$upscope $end
$scope task spi_send_word $end
$var reg 16 2 word [15:0] $end
$var integer 32 3 i [31:0] $end
$upscope $end
$upscope $end
$enddefinitions $end
$comment Show the parameter values. $end
$dumpall
$end
#0
$dumpvars
bx 3
bx 2
bx 1
bx 0
x/
x.
x-
x,
bx +
bx *
bx )
x(
0'
0&
1%
1$
0#
x"
bx !
$end
#1000
0(
0/
b0 *
b0 )
b0 1
b0 0
0$
#18500
0.
0-
0,
0"
b0 !
b0 +
1#
#37000
0#
#55500
1#
#74000
0#
#92500
1#
#111000
0#
#129500
1#
#148000
0#
#166500
1#
#185000
0#
#201000
1$
#203500
b1 0
1#
#222000
0#
#240500
1(
b11 0
1#
#259000
0#
#277500
1#
#296000
0#
#301000
0%
b1001000110100 2
#314500
1#
#333000
0#
#351000
b1111 3
#351500
1#
#370000
0#
#388500
1#
#401000
b1 )
1'
#407000
0#
#425500
1#
#444000
0#
#451000
b1110 3
0'
#462500
1#
#481000
0#
#499500
1#
#501000
b10 )
1'
#518000
0#
#536500
1#
#551000
b1101 3
0'
#555000
0#
#573500
1#
#592000
0#
#601000
b11 )
1'
#610500
1#
#629000
0#
#647500
1#
#651000
1&
b1100 3
0'
#666000
0#
#684500
1#
#701000
b100 )
b1 1
1'
#703000
0#
#721500
1#
#740000
0#
#751000
0&
b1011 3
0'
#758500
1#
#777000
0#
#795500
1#
#801000
b101 )
b10 1
1'
#814000
0#
#832500
1#
#851000
0#
b1010 3
0'
#869500
1#
#888000
0#
#901000
b110 )
b100 1
1'
#906500
1#
#925000
0#
#943500
1#
#951000
1&
b1001 3
0'
#962000
0#
#980500
1#
#999000
0#
#1001000
b111 )
b1001 1
1'
#1017500
1#
#1036000
0#
#1051000
0&
b1000 3
0'
#1054500
1#
#1073000
0#
#1091500
1#
#1101000
b1000 )
b10010 1
1'
#1110000
0#
#1128500
1#
#1147000
0#
#1151000
b111 3
0'
#1165500
1#
#1184000
0#
#1201000
b1001 )
b100100 1
1'
#1202500
1#
#1221000
0#
#1239500
1#
#1251000
b110 3
0'
#1258000
0#
#1276500
1#
#1295000
0#
#1301000
b1010 )
b1001000 1
1'
#1313500
1#
#1332000
0#
#1350500
1#
#1351000
1&
b101 3
0'
#1369000
0#
#1387500
1#
#1401000
b1011 )
b10010001 1
1'
#1406000
0#
#1424500
1#
#1443000
0#
#1451000
b100 3
0'
#1461500
1#
#1480000
0#
#1498500
1#
#1501000
b1100 )
b100100011 1
1'
#1517000
0#
#1535500
1#
#1551000
0&
b11 3
0'
#1554000
0#
#1572500
1#
#1591000
0#
#1601000
b1101 )
b1001000110 1
1'
#1609500
1#
#1628000
0#
#1646500
1#
#1651000
1&
b10 3
0'
#1665000
0#
#1683500
1#
#1701000
b1110 )
b10010001101 1
1'
#1702000
0#
#1720500
1#
#1739000
0#
#1751000
0&
b1 3
0'
#1757500
1#
#1776000
0#
#1794500
1#
#1801000
b1111 )
b100100011010 1
1'
#1813000
0#
#1831500
1#
#1850000
0#
#1851000
b0 3
0'
#1868500
1#
#1887000
0#
#1901000
b0 )
1/
b1001000110100 *
b1001000110100 1
1'
#1905500
1-
1#
#1924000
0#
#1942500
1.
1#
#1951000
b11111111111111111111111111111111 3
0'
#1961000
0#
#1971000
b1010101111001101 2
0%
#1979500
1"
b1001000110100 !
b1001000110100 +
1,
1#
#1998000
0#
#2016500
0"
1#
#2021000
1&
b1111 3
#2035000
0#
#2053500
1#
#2071000
b1 )
b10010001101001 1
1'
#2072000
0#
#2090500
1#
#2109000
0#
#2121000
0&
b1110 3
0'
#2127500
1#
#2146000
0#
#2164500
1#
#2171000
b10 )
b100100011010010 1
1'
#2183000
0#
#2201500
1#
#2220000
0#
#2221000
1&
b1101 3
0'
#2238500
1#
#2257000
0#
#2271000
b11 )
b1001000110100101 1
1'
#2275500
1#
#2294000
0#
#2312500
1#
#2321000
0&
b1100 3
0'
#2331000
0#
#2349500
1#
#2368000
0#
#2371000
b100 )
b10001101001010 1
1'
#2386500
1#
#2405000
0#
#2421000
1&
b1011 3
0'
#2423500
1#
#2442000
0#
#2460500
1#
#2471000
b101 )
b100011010010101 1
1'
#2479000
0#
#2497500
1#
#2516000
0#
#2521000
0&
b1010 3
0'
#2534500
1#
#2553000
0#
#2571000
b110 )
b1000110100101010 1
1'
#2571500
1#
#2590000
0#
#2608500
1#
#2621000
1&
b1001 3
0'
#2627000
0#
#2645500
1#
#2664000
0#
#2671000
b111 )
b1101001010101 1
1'
#2682500
1#
#2701000
0#
#2719500
1#
#2721000
b1000 3
0'
#2738000
0#
#2756500
1#
#2771000
b1000 )
b11010010101011 1
1'
#2775000
0#
#2793500
1#
#2812000
0#
#2821000
b111 3
0'
#2830500
1#
#2849000
0#
#2867500
1#
#2871000
b1001 )
b110100101010111 1
1'
#2886000
0#
#2904500
1#
#2921000
b110 3
0'
#2923000
0#
#2941500
1#
#2960000
0#
#2971000
b1010 )
b1101001010101111 1
1'
#2978500
1#
#2997000
0#
#3015500
1#
#3021000
0&
b101 3
0'
#3034000
0#
#3052500
1#
#3071000
b1011 )
b1010010101011110 1
0#
1'
#3089500
1#
#3108000
0#
#3121000
b100 3
0'
#3126500
1#
#3145000
0#
#3163500
1#
#3171000
b1100 )
b100101010111100 1
1'
#3182000
0#
#3200500
1#
#3219000
0#
#3221000
1&
b11 3
0'
#3237500
1#
#3256000
0#
#3271000
b1101 )
b1001010101111001 1
1'
#3274500
1#
#3293000
0#
#3311500
1#
#3321000
b10 3
0'
#3330000
0#
#3348500
1#
#3367000
0#
#3371000
b1110 )
b10101011110011 1
1'
#3385500
1#
#3404000
0#
#3421000
0&
b1 3
0'
#3422500
1#
#3441000
0#
#3459500
1#
#3471000
b1111 )
b101010111100110 1
1'
#3478000
0#
#3496500
1#
#3515000
0#
#3521000
1&
b0 3
0'
#3533500
1#
#3552000
0#
#3570500
1#
#3571000
b0 )
0/
b1010101111001101 *
b1010101111001101 1
1'
#3589000
0#
#3607500
0-
1#
#3621000
b11111111111111111111111111111111 3
0'
#3626000
0#
#3641000
b111100001111 2
0%
#3644500
0.
1#
#3663000
0#
#3681500
1"
b1010101111001101 !
b1010101111001101 +
0,
1#
#3691000
0&
b1111 3
#3700000
0#
#3718500
0"
1#
#3737000
0#
#3741000
b1 )
b101011110011010 1
1'
#3755500
1#
#3774000
0#
#3791000
b1110 3
0'
#3792500
1#
#3811000
0#
#3829500
1#
#3841000
b10 )
b1010111100110100 1
1'
#3848000
0#
#3866500
1#
#3885000
0#
#3891000
b1101 3
0'
#3903500
1#
#3922000
0#
#3940500
1#
#3941000
b11 )
b101111001101000 1
1'
#3959000
0#
#3977500
1#
#3991000
b1100 3
0'
#3996000
0#
#4014500
1#
#4033000
0#
#4041000
b100 )
b1011110011010000 1
1'
#4051500
1#
#4070000
0#
#4088500
1#
#4091000
1&
b1011 3
0'
#4107000
0#
#4125500
1#
#4141000
b101 )
b111100110100001 1
1'
#4144000
0#
#4162500
1#
#4181000
0#
#4191000
b1010 3
0'
#4199500
1#
#4218000
0#
#4236500
1#
#4241000
b110 )
b1111001101000011 1
1'
#4255000
0#
#4273500
1#
#4291000
b1001 3
0'
#4292000
0#
#4310500
1#
#4329000
0#
#4341000
b111 )
b1110011010000111 1
1'
#4347500
1#
#4366000
0#
#4384500
1#
#4391000
b1000 3
0'
#4403000
0#
#4421500
1#
#4440000
0#
#4441000
b1000 )
b1100110100001111 1
1'
#4458500
1#
#4477000
0#
#4491000
0&
b111 3
0'
#4495500
1#
#4514000
0#
#4532500
1#
#4541000
b1001 )
b1001101000011110 1
1'
#4551000
0#
#4569500
1#
#4588000
0#
#4591000
b110 3
0'
#4606500
1#
#4625000
0#
#4641000
b1010 )
b11010000111100 1
1'
#4643500
1#
#4662000
0#
#4680500
1#
#4691000
b101 3
0'
#4699000
0#
#4717500
1#
#4736000
0#
#4741000
b1011 )
b110100001111000 1
1'
#4754500
1#
#4773000
0#
#4791000
b100 3
0'
#4791500
1#
#4810000
0#
#4828500
1#
#4841000
b1100 )
b1101000011110000 1
1'
#4847000
0#
#4865500
1#
#4884000
0#
#4891000
1&
b11 3
0'
#4902500
1#
#4921000
0#
#4939500
1#
#4941000
b1101 )
b1010000111100001 1
1'
#4958000
0#
#4976500
1#
#4991000
b10 3
0'
#4995000
0#
#5013500
1#
#5032000
0#
#5041000
b1110 )
b100001111000011 1
1'
#5050500
1#
#5069000
0#
#5087500
1#
#5091000
b1 3
0'
#5106000
0#
#5124500
1#
#5141000
b1111 )
b1000011110000111 1
1'
#5143000
0#
#5161500
1#
#5180000
0#
#5191000
b0 3
0'
#5198500
1#
#5217000
0#
#5235500
1#
#5241000
b0 )
1/
b111100001111 *
b111100001111 1
1'
#5254000
0#
#5272500
1-
1#
#5291000
0#
b11111111111111111111111111111111 3
0'
#5309500
1.
1#
#5311000
1%
#5328000
0#
#5346500
1"
b111100001111 !
b111100001111 +
1,
1#
#5365000
0#
#5383500
0"
1#
