src/fpga/spi_shifter.v
module spi_byte_shifter #(
    parameter integer CLK_DIV = 4  // sysclk ticks per half SCK
) (
    input  wire clk,
    input  wire reset_n,
    input  wire start,
    input  wire [7:0] tx_byte,
    input  wire mosi_oe,           // drive MOSI when 1
    output reg  [7:0] rx_byte,
    output reg  busy,
    output reg  sck,
    output reg  mosi,
    input  wire miso,
    output reg  done
);
    reg [7:0] shreg;
    reg [3:0] bitcnt;
    reg [$clog2(CLK_DIV*2)-1:0] divcnt;

    always @(posedge clk or negedge reset_n) begin
        if (!reset_n) begin
            busy <= 0; done <= 0; sck <= 0; mosi <= 0; rx_byte <= 0;
            bitcnt <= 0; divcnt <= 0; shreg <= 0;
        end else begin
            done <= 1'b0;
            if (start && !busy) begin
                busy   <= 1'b1;
                shreg  <= tx_byte;
                bitcnt <= 4'd8;
                divcnt <= 0;
                sck    <= 1'b0;
                mosi   <= tx_byte[7];
            end else if (busy) begin
                divcnt <= divcnt + 1'b1;
                if (divcnt == CLK_DIV-1) begin
                    sck <= 1'b1; // rising edge: sample MISO
                end else if (divcnt == CLK_DIV*2-1) begin
                    // falling edge: shift out next bit
                    divcnt <= 0;
                    shreg <= {shreg[6:0], miso};
                    bitcnt <= bitcnt - 1'b1;
                    sck <= 1'b0;
                    mosi <= shreg[6];
                    if (bitcnt == 1) begin
                        busy <= 1'b0;
                        done <= 1'b1;
                        rx_byte <= {shreg[6:0], miso};
                        mosi <= 1'b0;
                    end
                end
            end
            if (!mosi_oe) mosi <= 1'b0; // tri-state externally with OBUFT if needed
        end
    end
endmodule

src/fpga/flash_page.v
module w25q64_page_logger #(
    parameter integer CLK_DIV    = 4,
    parameter [23:0]  START_ADDR = 24'h100000
) (
    input  wire clk,
    input  wire reset_n,
    // Page buffer interface
    input  wire [7:0] buf_dout,
    output reg  [7:0] buf_addr,
    input  wire       buf_full,
    input  wire       buf_flush,
    // SPI pins
    output wire spi_sck,
    output wire spi_mosi,
    input  wire spi_miso,
    output reg  spi_csn,
    // Status
    output reg  busy
);
    localparam [7:0] CMD_WREN = 8'h06;
    localparam [7:0] CMD_PP   = 8'h02;
    localparam [7:0] CMD_RDSR = 8'h05;

    localparam [3:0] S_IDLE           = 4'd0;
    localparam [3:0] S_WREN_WAIT      = 4'd1;
    localparam [3:0] S_PP_HDR_START   = 4'd2;
    localparam [3:0] S_PP_HDR_WAIT    = 4'd3;
    localparam [3:0] S_PP_DATA_START  = 4'd4;
    localparam [3:0] S_PP_DATA_WAIT   = 4'd5;
    localparam [3:0] S_RDSR_CMD_START = 4'd6;
    localparam [3:0] S_RDSR_CMD_WAIT  = 4'd7;
    localparam [3:0] S_RDSR_DATA_START= 4'd8;
    localparam [3:0] S_RDSR_DATA_WAIT = 4'd9;

    wire start_write = buf_full; // Partial-page flush is intentionally disabled for now.

    reg  [3:0]  state;
    reg  [1:0]  hdr_idx;
    reg  [7:0]  byte_cnt;
    reg  [23:0] addr;
    reg         sh_start;
    reg  [7:0]  sh_tx;
    wire [7:0]  sh_rx;
    wire        sh_busy;
    wire        sh_done;

    // Keep the port in the interface so the module shape stays stable until
    // partial-page support is implemented.
    wire unused_buf_flush = buf_flush;

    spi_byte_shifter #(.CLK_DIV(CLK_DIV)) sh (
        .clk     (clk),
        .reset_n (reset_n),
        .start   (sh_start),
        .tx_byte (sh_tx),
        .mosi_oe (1'b1),
        .rx_byte (sh_rx),
        .busy    (sh_busy),
        .sck     (spi_sck),
        .mosi    (spi_mosi),
        .miso    (spi_miso),
        .done    (sh_done)
    );

    always @(posedge clk) begin
        if (!reset_n) begin
            state    <= S_IDLE;
            hdr_idx  <= 2'd0;
            byte_cnt <= 8'd0;
            addr     <= START_ADDR;
            buf_addr <= 8'd0;
            sh_start <= 1'b0;
            sh_tx    <= 8'd0;
            spi_csn  <= 1'b1;
            busy     <= 1'b0;
        end else begin
            sh_start <= 1'b0;

            case (state)
                S_IDLE: begin
                    busy    <= 1'b0;
                    spi_csn <= 1'b1;
                    if (start_write) begin
                        busy     <= 1'b1;
                        spi_csn  <= 1'b0;
                        sh_tx    <= CMD_WREN;
                        sh_start <= 1'b1;
                        state    <= S_WREN_WAIT;
                    end
                end

                S_WREN_WAIT: begin
                    if (sh_done) begin
                        spi_csn  <= 1'b1;
                        hdr_idx  <= 2'd0;
                        byte_cnt <= 8'd0;
                        state    <= S_PP_HDR_START;
                    end
                end

                S_PP_HDR_START: begin
                    spi_csn <= 1'b0;
                    if (!sh_busy) begin
                        case (hdr_idx)
                            2'd0: sh_tx <= CMD_PP;
                            2'd1: sh_tx <= addr[23:16];
                            2'd2: sh_tx <= addr[15:8];
                            default: sh_tx <= addr[7:0];
                        endcase
                        sh_start <= 1'b1;
                        state    <= S_PP_HDR_WAIT;
                    end
                end

                S_PP_HDR_WAIT: begin
                    if (sh_done) begin
                        if (hdr_idx == 2'd3) begin
                            buf_addr <= 8'd0;
                            state    <= S_PP_DATA_START;
                        end else begin
                            hdr_idx <= hdr_idx + 2'd1;
                            state   <= S_PP_HDR_START;
                        end
                    end
                end

                S_PP_DATA_START: begin
                    if (!sh_busy) begin
                        sh_tx    <= buf_dout;
                        sh_start <= 1'b1;
                        state    <= S_PP_DATA_WAIT;
                    end
                end

                S_PP_DATA_WAIT: begin
                    if (sh_done) begin
                        if (byte_cnt == 8'hFF) begin
                            spi_csn <= 1'b1; // Finish the page program command before polling.
                            state   <= S_RDSR_CMD_START;
                        end else begin
                            byte_cnt <= byte_cnt + 8'd1;
                            buf_addr <= buf_addr + 8'd1;
                            state    <= S_PP_DATA_START;
                        end
                    end
                end

                S_RDSR_CMD_START: begin
                    spi_csn <= 1'b0;
                    if (!sh_busy) begin
                        sh_tx    <= CMD_RDSR;
                        sh_start <= 1'b1;
                        state    <= S_RDSR_CMD_WAIT;
                    end
                end

                S_RDSR_CMD_WAIT: begin
                    if (sh_done) begin
                        state <= S_RDSR_DATA_START;
                    end
                end

                S_RDSR_DATA_START: begin
                    if (!sh_busy) begin
                        sh_tx    <= 8'hFF;
                        sh_start <= 1'b1;
                        state    <= S_RDSR_DATA_WAIT;
                    end
                end

                S_RDSR_DATA_WAIT: begin
                    if (sh_done) begin
                        spi_csn <= 1'b1;
                        if (sh_rx[0] == 1'b0) begin
                            addr  <= addr + 24'd256;
                            busy  <= 1'b0;
                            state <= S_IDLE;
                        end else begin
                            state <= S_RDSR_CMD_START;
                        end
                    end
                end

                default: begin
                    state <= S_IDLE;
                end
            endcase
        end
    end
endmodule

test/sim/w25q64_page_logger_tb.v
// purpose is to verify the command sequence, and to check cs/sclk/mosi toggling
`timescale 1ns/1ps

module w25q64_page_logger_tb;

    reg clk = 0;
    reg reset_n = 0;

    reg [7:0] buf_mem [0:255];
    wire [7:0] buf_addr;
    wire [7:0] buf_dout = buf_mem[buf_addr];

    reg buf_full = 0;
    wire spi_sck, spi_mosi;
    reg spi_miso = 1'b1;
    wire spi_csn;
    wire busy;

    always #10 clk = ~clk;

    w25q64_page_logger dut (
        .clk(clk),
        .reset_n(reset_n),
        .buf_dout(buf_dout),
        .buf_addr(buf_addr),
        .buf_full(buf_full),
        .buf_flush(1'b0),
        .spi_sck(spi_sck),
        .spi_mosi(spi_mosi),
        .spi_miso(spi_miso),
        .spi_csn(spi_csn),
        .busy(busy)
    );

    integer i;

    initial begin
        $dumpfile("w25q64_page_logger_tb.vcd");
        $dumpvars(0, w25q64_page_logger_tb);

        for (i = 0; i < 256; i = i + 1)
            buf_mem[i] = i;

        reset_n = 0;
        #100 reset_n = 1;

        #200 buf_full = 1;
        #50 buf_full = 0;

        #5000;
        $finish;
    end
endmodule
//expected behavior: cs goes low, 06 wren, 02 pp, address, 256 bytes, rdsr polling loop

test/w25q64_page_logger_tb.vcd
$date
	Sat Mar 07 13:48:10 2026
$end
$version
	Icarus Verilog
$end
$timescale
	1ps
$end
$scope module w25q64_page_logger_tb $end
$var wire 8 ! buf_dout [7:0] $end
$var wire 1 " spi_sck $end
$var wire 1 # spi_mosi $end
$var wire 1 $ spi_csn $end
$var wire 1 % busy $end
$var wire 8 & buf_addr [7:0] $end
$var reg 1 ' buf_full $end
$var reg 1 ( clk $end
$var reg 1 ) reset_n $end
$var reg 1 * spi_miso $end
$var integer 32 + i [31:0] $end
$scope module dut $end
$var wire 8 , buf_dout [7:0] $end
$var wire 1 - buf_flush $end
$var wire 1 ' buf_full $end
$var wire 1 ( clk $end
$var wire 1 ) reset_n $end
$var wire 1 * spi_miso $end
$var wire 1 . start_write $end
$var wire 1 / unused_buf_flush $end
$var wire 1 " spi_sck $end
$var wire 1 # spi_mosi $end
$var wire 8 0 sh_rx [7:0] $end
$var wire 1 1 sh_done $end
$var wire 1 2 sh_busy $end
$var parameter 32 3 CLK_DIV $end
$var parameter 8 4 CMD_PP $end
$var parameter 8 5 CMD_RDSR $end
$var parameter 8 6 CMD_WREN $end
$var parameter 24 7 START_ADDR $end
$var parameter 4 8 S_IDLE $end
$var parameter 4 9 S_PP_DATA_START $end
$var parameter 4 : S_PP_DATA_WAIT $end
$var parameter 4 ; S_PP_HDR_START $end
$var parameter 4 < S_PP_HDR_WAIT $end
$var parameter 4 = S_RDSR_CMD_START $end
$var parameter 4 > S_RDSR_CMD_WAIT $end
$var parameter 4 ? S_RDSR_DATA_START $end
$var parameter 4 @ S_RDSR_DATA_WAIT $end
$var parameter 4 A S_WREN_WAIT $end
$var reg 24 B addr [23:0] $end
$var reg 8 C buf_addr [7:0] $end
$var reg 1 % busy $end
$var reg 8 D byte_cnt [7:0] $end
$var reg 2 E hdr_idx [1:0] $end
$var reg 1 F sh_start $end
$var reg 8 G sh_tx [7:0] $end
$var reg 1 $ spi_csn $end
$var reg 4 H state [3:0] $end
$scope module sh $end
$var wire 1 ( clk $end
$var wire 1 * miso $end
$var wire 1 I mosi_oe $end
$var wire 1 ) reset_n $end
$var wire 1 F start $end
$var wire 8 J tx_byte [7:0] $end
$var parameter 32 K CLK_DIV $end
$var reg 4 L bitcnt [3:0] $end
$var reg 1 2 busy $end
$var reg 3 M divcnt [2:0] $end
$var reg 1 1 done $end
$var reg 1 # mosi $end
$var reg 8 N rx_byte [7:0] $end
$var reg 1 " sck $end
$var reg 8 O shreg [7:0] $end
$upscope $end
$upscope $end
$upscope $end
$enddefinitions $end
$comment Show the parameter values. $end
$dumpall
b100 K
b1 A
b1001 @
b1000 ?
b111 >
b110 =
b11 <
b10 ;
b101 :
b100 9
b0 8
b100000000000000000000 7
b110 6
b101 5
b10 4
b100 3
$end
#0
$dumpvars
bx O
bx N
bx M
bx L
bx J
1I
bx H
bx G
xF
bx E
bx D
bx C
bx B
x2
x1
bx 0
0/
0.
0-
bx ,
b100000000 +
1*
0)
0(
0'
bx &
x%
x$
x#
x"
bx !
$end
#10000
b0 O
b0 M
b0 L
b0 0
b0 N
0#
0"
01
02
0%
1$
b0 G
b0 J
0F
b0 !
b0 ,
b0 &
b0 C
b100000000000000000000 B
b0 D
b0 E
b0 H
1(
#20000
0(
#30000
1(
#40000
0(
#50000
1(
#60000
0(
#70000
1(
#80000
0(
#90000
1(
#100000
0(
1)
#110000
1(
#120000
0(
#130000
1(
#140000
0(
#150000
1(
#160000
0(
#170000
1(
#180000
0(
#190000
1(
#200000
0(
#210000
1(
#220000
0(
#230000
1(
#240000
0(
#250000
1(
#260000
0(
#270000
1(
#280000
0(
#290000
1(
#300000
0(
1.
1'
#310000
b1 H
1F
b110 G
b110 J
0$
1%
1(
#320000
0(
#330000
b1000 L
b110 O
12
0F
1(
#340000
0(
#350000
b1 M
1(
0.
0'
#360000
0(
#370000
b10 M
1(
#380000
0(
#390000
b11 M
1(
#400000
0(
#410000
1"
b100 M
1(
#420000
0(
#430000
b101 M
1(
#440000
0(
#450000
b110 M
1(
#460000
0(
#470000
b111 M
1(
#480000
0(
#490000
0"
b111 L
b1101 O
b0 M
1(
#500000
0(
#510000
b1 M
1(
#520000
0(
#530000
b10 M
1(
#540000
0(
#550000
b11 M
1(
#560000
0(
#570000
1"
b100 M
1(
#580000
0(
#590000
b101 M
1(
#600000
0(
#610000
b110 M
1(
#620000
0(
#630000
b111 M
1(
#640000
0(
#650000
0"
b110 L
b11011 O
b0 M
1(
#660000
0(
#670000
b1 M
1(
#680000
0(
#690000
b10 M
1(
#700000
0(
#710000
b11 M
1(
#720000
0(
#730000
1"
b100 M
1(
#740000
0(
#750000
b101 M
1(
#760000
0(
#770000
b110 M
1(
#780000
0(
#790000
b111 M
1(
#800000
0(
#810000
0"
b101 L
b110111 O
b0 M
1(
#820000
0(
#830000
b1 M
1(
#840000
0(
#850000
b10 M
1(
#860000
0(
#870000
b11 M
1(
#880000
0(
#890000
1"
b100 M
1(
#900000
0(
#910000
b101 M
1(
#920000
0(
#930000
b110 M
1(
#940000
0(
#950000
b111 M
1(
#960000
0(
#970000
0"
b100 L
b1101111 O
b0 M
1(
#980000
0(
#990000
b1 M
1(
#1000000
0(
#1010000
b10 M
1(
#1020000
0(
#1030000
b11 M
1(
#1040000
0(
#1050000
1"
b100 M
1(
#1060000
0(
#1070000
b101 M
1(
#1080000
0(
#1090000
b110 M
1(
#1100000
0(
#1110000
b111 M
1(
#1120000
0(
#1130000
1#
0"
b11 L
b11011111 O
b0 M
1(
#1140000
0(
#1150000
b1 M
1(
#1160000
0(
#1170000
b10 M
1(
#1180000
0(
#1190000
b11 M
1(
#1200000
0(
#1210000
1"
b100 M
1(
#1220000
0(
#1230000
b101 M
1(
#1240000
0(
#1250000
b110 M
1(
#1260000
0(
#1270000
b111 M
1(
#1280000
0(
#1290000
0"
b10 L
b10111111 O
b0 M
1(
#1300000
0(
#1310000
b1 M
1(
#1320000
0(
#1330000
b10 M
1(
#1340000
0(
#1350000
b11 M
1(
#1360000
0(
#1370000
1"
b100 M
1(
#1380000
0(
#1390000
b101 M
1(
#1400000
0(
#1410000
b110 M
1(
#1420000
0(
#1430000
b111 M
1(
#1440000
0(
#1450000
0#
0"
b1 L
b1111111 O
b0 M
1(
#1460000
0(
#1470000
b1 M
1(
#1480000
0(
#1490000
b10 M
1(
#1500000
0(
#1510000
b11 M
1(
#1520000
0(
#1530000
1"
b100 M
1(
#1540000
0(
#1550000
b101 M
1(
#1560000
0(
#1570000
b110 M
1(
#1580000
0(
#1590000
b111 M
1(
#1600000
0(
#1610000
b11111111 0
b11111111 N
11
02
0#
0"
b0 L
b11111111 O
b0 M
1(
#1620000
0(
#1630000
b10 H
1$
01
1(
#1640000
0(
#1650000
b11 H
1F
b10 G
b10 J
0$
1(
#1660000
0(
#1670000
0F
b1000 L
b10 O
12
1(
#1680000
0(
#1690000
b1 M
1(
#1700000
0(
#1710000
b10 M
1(
#1720000
0(
#1730000
b11 M
1(
#1740000
0(
#1750000
1"
b100 M
1(
#1760000
0(
#1770000
b101 M
1(
#1780000
0(
#1790000
b110 M
1(
#1800000
0(
#1810000
b111 M
1(
#1820000
0(
#1830000
0"
b111 L
b101 O
b0 M
1(
#1840000
0(
#1850000
b1 M
1(
#1860000
0(
#1870000
b10 M
1(
#1880000
0(
#1890000
b11 M
1(
#1900000
0(
#1910000
1"
b100 M
1(
#1920000
0(
#1930000
b101 M
1(
#1940000
0(
#1950000
b110 M
1(
#1960000
0(
#1970000
b111 M
1(
#1980000
0(
#1990000
0"
b110 L
b1011 O
b0 M
1(
#2000000
0(
#2010000
b1 M
1(
#2020000
0(
#2030000
b10 M
1(
#2040000
0(
#2050000
b11 M
1(
#2060000
0(
#2070000
1"
b100 M
1(
#2080000
0(
#2090000
b101 M
1(
#2100000
0(
#2110000
b110 M
1(
#2120000
0(
#2130000
b111 M
1(
#2140000
0(
#2150000
0"
b101 L
b10111 O
b0 M
1(
#2160000
0(
#2170000
b1 M
1(
#2180000
0(
#2190000
b10 M
1(
#2200000
0(
#2210000
b11 M
1(
#2220000
0(
#2230000
1"
b100 M
1(
#2240000
0(
#2250000
b101 M
1(
#2260000
0(
#2270000
b110 M
1(
#2280000
0(
#2290000
b111 M
1(
#2300000
0(
#2310000
0"
b100 L
b101111 O
b0 M
1(
#2320000
0(
#2330000
b1 M
1(
#2340000
0(
#2350000
b10 M
1(
#2360000
0(
#2370000
b11 M
1(
#2380000
0(
#2390000
1"
b100 M
1(
#2400000
0(
#2410000
b101 M
1(
#2420000
0(
#2430000
b110 M
1(
#2440000
0(
#2450000
b111 M
1(
#2460000
0(
#2470000
0"
b11 L
b1011111 O
b0 M
1(
#2480000
0(
#2490000
b1 M
1(
#2500000
0(
#2510000
b10 M
1(
#2520000
0(
#2530000
b11 M
1(
#2540000
0(
#2550000
1"
b100 M
1(
#2560000
0(
#2570000
b101 M
1(
#2580000
0(
#2590000
b110 M
1(
#2600000
0(
#2610000
b111 M
1(
#2620000
0(
#2630000
1#
0"
b10 L
b10111111 O
b0 M
1(
#2640000
0(
#2650000
b1 M
1(
#2660000
0(
#2670000
b10 M
1(
#2680000
0(
#2690000
b11 M
1(
#2700000
0(
#2710000
1"
b100 M
1(
#2720000
0(
#2730000
b101 M
1(
#2740000
0(
#2750000
b110 M
1(
#2760000
0(
#2770000
b111 M
1(
#2780000
0(
#2790000
0#
0"
b1 L
b1111111 O
b0 M
1(
#2800000
0(
#2810000
b1 M
1(
#2820000
0(
#2830000
b10 M
1(
#2840000
0(
#2850000
b11 M
1(
#2860000
0(
#2870000
1"
b100 M
1(
#2880000
0(
#2890000
b101 M
1(
#2900000
0(
#2910000
b110 M
1(
#2920000
0(
#2930000
b111 M
1(
#2940000
0(
#2950000
11
02
0#
0"
b0 L
b11111111 O
b0 M
1(
#2960000
0(
#2970000
01
b10 H
b1 E
1(
#2980000
0(
#2990000
b11 H
1F
b10000 G
b10000 J
1(
#3000000
0(
#3010000
b1000 L
b10000 O
12
0F
1(
#3020000
0(
#3030000
b1 M
1(
#3040000
0(
#3050000
b10 M
1(
#3060000
0(
#3070000
b11 M
1(
#3080000
0(
#3090000
1"
b100 M
1(
#3100000
0(
#3110000
b101 M
1(
#3120000
0(
#3130000
b110 M
1(
#3140000
0(
#3150000
b111 M
1(
#3160000
0(
#3170000
0"
b111 L
b100001 O
b0 M
1(
#3180000
0(
#3190000
b1 M
1(
#3200000
0(
#3210000
b10 M
1(
#3220000
0(
#3230000
b11 M
1(
#3240000
0(
#3250000
1"
b100 M
1(
#3260000
0(
#3270000
b101 M
1(
#3280000
0(
#3290000
b110 M
1(
#3300000
0(
#3310000
b111 M
1(
#3320000
0(
#3330000
0"
b110 L
b1000011 O
b0 M
1(
#3340000
0(
#3350000
b1 M
1(
#3360000
0(
#3370000
b10 M
1(
#3380000
0(
#3390000
b11 M
1(
#3400000
0(
#3410000
1"
b100 M
1(
#3420000
0(
#3430000
b101 M
1(
#3440000
0(
#3450000
b110 M
1(
#3460000
0(
#3470000
b111 M
1(
#3480000
0(
#3490000
1#
0"
b101 L
b10000111 O
b0 M
1(
#3500000
0(
#3510000
b1 M
1(
#3520000
0(
#3530000
b10 M
1(
#3540000
0(
#3550000
b11 M
1(
#3560000
0(
#3570000
1"
b100 M
1(
#3580000
0(
#3590000
b101 M
1(
#3600000
0(
#3610000
b110 M
1(
#3620000
0(
#3630000
b111 M
1(
#3640000
0(
#3650000
0#
0"
b100 L
b1111 O
b0 M
1(
#3660000
0(
#3670000
b1 M
1(
#3680000
0(
#3690000
b10 M
1(
#3700000
0(
#3710000
b11 M
1(
#3720000
0(
#3730000
1"
b100 M
1(
#3740000
0(
#3750000
b101 M
1(
#3760000
0(
#3770000
b110 M
1(
#3780000
0(
#3790000
b111 M
1(
#3800000
0(
#3810000
0"
b11 L
b11111 O
b0 M
1(
#3820000
0(
#3830000
b1 M
1(
#3840000
0(
#3850000
b10 M
1(
#3860000
0(
#3870000
b11 M
1(
#3880000
0(
#3890000
1"
b100 M
1(
#3900000
0(
#3910000
b101 M
1(
#3920000
0(
#3930000
b110 M
1(
#3940000
0(
#3950000
b111 M
1(
#3960000
0(
#3970000
0"
b10 L
b111111 O
b0 M
1(
#3980000
0(
#3990000
b1 M
1(
#4000000
0(
#4010000
b10 M
1(
#4020000
0(
#4030000
b11 M
1(
#4040000
0(
#4050000
1"
b100 M
1(
#4060000
0(
#4070000
b101 M
1(
#4080000
0(
#4090000
b110 M
1(
#4100000
0(
#4110000
b111 M
1(
#4120000
0(
#4130000
0"
b1 L
b1111111 O
b0 M
1(
#4140000
0(
#4150000
b1 M
1(
#4160000
0(
#4170000
b10 M
1(
#4180000
0(
#4190000
b11 M
1(
#4200000
0(
#4210000
1"
b100 M
1(
#4220000
0(
#4230000
b101 M
1(
#4240000
0(
#4250000
b110 M
1(
#4260000
0(
#4270000
b111 M
1(
#4280000
0(
#4290000
11
02
0#
0"
b0 L
b11111111 O
b0 M
1(
#4300000
0(
#4310000
b10 H
b10 E
01
1(
#4320000
0(
#4330000
b11 H
1F
b0 G
b0 J
1(
#4340000
0(
#4350000
0F
b1000 L
b0 O
12
1(
#4360000
0(
#4370000
b1 M
1(
#4380000
0(
#4390000
b10 M
1(
#4400000
0(
#4410000
b11 M
1(
#4420000
0(
#4430000
1"
b100 M
1(
#4440000
0(
#4450000
b101 M
1(
#4460000
0(
#4470000
b110 M
1(
#4480000
0(
#4490000
b111 M
1(
#4500000
0(
#4510000
0"
b111 L
b1 O
b0 M
1(
#4520000
0(
#4530000
b1 M
1(
#4540000
0(
#4550000
b10 M
1(
#4560000
0(
#4570000
b11 M
1(
#4580000
0(
#4590000
1"
b100 M
1(
#4600000
0(
#4610000
b101 M
1(
#4620000
0(
#4630000
b110 M
1(
#4640000
0(
#4650000
b111 M
1(
#4660000
0(
#4670000
0"
b110 L
b11 O
b0 M
1(
#4680000
0(
#4690000
b1 M
1(
#4700000
0(
#4710000
b10 M
1(
#4720000
0(
#4730000
b11 M
1(
#4740000
0(
#4750000
1"
b100 M
1(
#4760000
0(
#4770000
b101 M
1(
#4780000
0(
#4790000
b110 M
1(
#4800000
0(
#4810000
b111 M
1(
#4820000
0(
#4830000
0"
b101 L
b111 O
b0 M
1(
#4840000
0(
#4850000
b1 M
1(
#4860000
0(
#4870000
b10 M
1(
#4880000
0(
#4890000
b11 M
1(
#4900000
0(
#4910000
1"
b100 M
1(
#4920000
0(
#4930000
b101 M
1(
#4940000
0(
#4950000
b110 M
1(
#4960000
0(
#4970000
b111 M
1(
#4980000
0(
#4990000
0"
b100 L
b1111 O
b0 M
1(
#5000000
0(
#5010000
b1 M
1(
#5020000
0(
#5030000
b10 M
1(
#5040000
0(
#5050000
b11 M
1(
#5060000
0(
#5070000
1"
b100 M
1(
#5080000
0(
#5090000
b101 M
1(
#5100000
0(
#5110000
b110 M
1(
#5120000
0(
#5130000
b111 M
1(
#5140000
0(
#5150000
0"
b11 L
b11111 O
b0 M
1(
#5160000
0(
#5170000
b1 M
1(
#5180000
0(
#5190000
b10 M
1(
#5200000
0(
#5210000
b11 M
1(
#5220000
0(
#5230000
1"
b100 M
1(
#5240000
0(
#5250000
b101 M
1(
#5260000
0(
#5270000
b110 M
1(
#5280000
0(
#5290000
b111 M
1(
#5300000
0(
#5310000
0"
b10 L
b111111 O
b0 M
1(
#5320000
0(
#5330000
b1 M
1(
#5340000
0(
#5350000
b10 M
1(
